ascenderai/__init__.py
ascenderai/ascender_ai.py
ascenderai/errors.py
ascenderai/handler.py
ascenderai/langchain_embedding.py
ascenderai/langchain_llm.py
ascenderai/types.py
ascenderai-0.1.2.dist-info/METADATA
ascenderai-0.1.2.dist-info/WHEEL
ascenderai-0.1.2.dist-info/RECORD
