Metadata-Version: 2.1
Name: ascenderai
Version: 0.1.2
Summary: Python SDK library for interacting with AscenderAI clusters
Author: AscenderTeam
Author-email: info@ascender.space
Requires-Python: >=3.11,<4.0
Classifier: Programming Language :: Python :: 3
Classifier: Programming Language :: Python :: 3.11
Requires-Dist: aiohttp (==3.9.3)
Requires-Dist: langchain (>=0.1.7,<0.2.0)
Requires-Dist: langchain-community (>=0.0.20,<0.0.21)
Requires-Dist: rich (>=13.7.0,<14.0.0)
